eu2019model/__init__.py
eu2019model/constants.py
eu2019model/dhondt.py
eu2019model/models.py
eu2019model/recommend.py
eu2019model/utilities.py
eu2019model-1.3.0.dist-info/AUTHORS.rst
eu2019model-1.3.0.dist-info/LICENSE
eu2019model-1.3.0.dist-info/METADATA
eu2019model-1.3.0.dist-info/WHEEL
eu2019model-1.3.0.dist-info/entry_points.txt
eu2019model-1.3.0.dist-info/top_level.txt
eu2019model-1.3.0.dist-info/RECORD
