Metadata-Version: 2.1
Name: eu2019model
Version: 1.3.0
Summary: Model to be used as a recommendation engine for people wishing to vote remain in the EU 2019 elections in the UK
Home-page: https://github.com/remainvoter/eu2019model
Author: Nicholas Martin
Author-email: drnicholasdmartin@gmail.com
License: MIT license
Keywords: eu2019model
Platform: UNKNOWN
Classifier: Development Status :: 5 - Production/Stable
Classifier: License :: OSI Approved :: MIT License
Classifier: Natural Language :: English
Classifier: Programming Language :: Python :: 3.7
Requires-Dist: requests (==2.22.0)
